tinda/__init__.py
tinda/audioVideoClient.py
tinda/bot.py
tinda/functions.py
tinda/sock.py
tinda/terClient.py
tinda/terServer.py
tinda/tercli.py
tinda/terser.py
tinda/test.py
tinda/zzz.py
tinda-0.0.30.dist-info/LICENSE.txt
tinda-0.0.30.dist-info/METADATA
tinda-0.0.30.dist-info/WHEEL
tinda-0.0.30.dist-info/top_level.txt
tinda-0.0.30.dist-info/RECORD
