Metadata-Version: 2.1
Name: tinda
Version: 0.0.30
Summary: BUGGY ALPHA STATE
Home-page: UNKNOWN
Author: (Hank Singh)
Author-email: <hanksingh07@gmail.com>
License: UNKNOWN
Keywords: python
Platform: UNKNOWN
Classifier: Development Status :: 1 - Planning
Classifier: Programming Language :: Python :: 3
Classifier: Operating System :: Unix
Classifier: Operating System :: Microsoft :: Windows
License-File: LICENSE.txt
Requires-Dist: numpy
Requires-Dist: argparse
Requires-Dist: wave
Requires-Dist: pyautogui
Requires-Dist: mediapipe
Requires-Dist: tqdm
Requires-Dist: opencv-python
Requires-Dist: twine
Requires-Dist: pyttsx3
Requires-Dist: pyaudio
Requires-Dist: speedtest-cli
Requires-Dist: pynput
Requires-Dist: datetime
Requires-Dist: bs4
Requires-Dist: SpeechRecognition
